{
  "schemaVersion": 1,
  "id": "${id}",
  "version": "${version}",
  "name": "${name}",
  "description": "Adds wood types for huge mushrooms.",
  "authors": [ "Team Aurora" ],
  "contributors": [ "StevePlayzz_", "JustoPlayzz_", "ex0planetary", "mcvinnyq" ],
  "contact": {
    "homepage": "https://discord.gg/teamaurora",
	"issues": "https://github.com/TeamAuroraMods/${repo}/issues",
    "sources": "https://github.com/TeamAuroraMods/${repo}/"
  },
  "license": "GPLv3",
  "icon": "icon.png",
  "environment": "*",
  "mixins": [
    "${id}-common.mixins.json",
    "${id}.mixins.json"
  ],
  "entrypoints": {
    "main": [
      "com.teamaurora.enhanced_mushrooms.core.fabric.EnhancedMushroomsFabric"
    ],
    "client": [
      "com.teamaurora.enhanced_mushrooms.client.fabric.EMClient"
    ]
  },
  "depends": {
    "fabric": "*",
    "minecraft": "1.18.x",
    "pollen": "1.0.0"
  }
}